RemueveSecretos
