Metadata-Version: 1.1
Name: RemueveSecretos
Version: 1.0.1
Summary: Remueve o muestra secretos para desarrollo evitando filtrar informacion no deseada en nube
Home-page: https://github.com/FrEaKAlL/RemueveSecretos.git
Author: FrEaKAlL
Author-email: sercal0121@gmail.com
License: MIT
Platform: UNKNOWN
Classifier: Development Status :: 2 - Pre-Alpha
Classifier: License :: OSI Approved :: MIT License
Classifier: Programming Language :: Python
Classifier: Programming Language :: Python :: 2
Classifier: Programming Language :: Python :: 2.7
Classifier: Programming Language :: Python :: 3
Classifier: Programming Language :: Python :: 3.4
Classifier: Programming Language :: Python :: 3.5
Classifier: Programming Language :: Python :: 3.6
Classifier: Programming Language :: Python :: 3.7
